{
  "@type": "earl:TestResult",
  "spec": "holo-availability — the honest bytes-vs-metadata resolver: a discovered TMDb title binds to a source the user actually holds (by TMDb id, else normalized title with a year guard), best source by priority (owned κ > κ-store > server > open) wins, and an unheld title stays browse-only. Turns 'request' into 'play' without faking bytes.",
  "authority": "rests on #holo-availability — Phase 2 of the streaming/metadata plan",
  "witnessed": true,
  "covers": [
    "binds-by-title",
    "binds-by-tmdb-id",
    "priority-wins",
    "year-guard",
    "browse-when-no-match",
    "availability-shape"
  ],
  "checks": {
    "bindsByTitle": true,
    "bindsByTmdbId": true,
    "priorityWins": true,
    "yearGuard": true,
    "browseWhenNoMatch": true,
    "availabilityShape": true
  },
  "failed": []
}
